experience_recorder/__init__.py
experience_recorder/configuration/__init__.py
experience_recorder/configuration/configuration.py
experience_recorder/main.py
experience_recorder/perceptions/__init__.py
experience_recorder/perceptions/perceptions.py
experience_recorder/recorder/__init__.py
experience_recorder/recorder/recorder.py
experience_recorder/senses/__init__.py
experience_recorder/senses/senses.py
experience_recorder-0.2.0.dist-info/METADATA
experience_recorder-0.2.0.dist-info/WHEEL
experience_recorder-0.2.0.dist-info/RECORD
