Metadata-Version: 2.1
Name: experience-recorder
Version: 0.2.0
Summary: 
Author: frapercan
Author-email: frapercan1@alum.us.es
Requires-Python: >=3.10,<4.0
Classifier: Programming Language :: Python :: 3
Classifier: Programming Language :: Python :: 3.10
Classifier: Programming Language :: Python :: 3.11
Requires-Dist: docopt (>=0.6.2,<0.7.0)
Requires-Dist: numpy (>=1.24.2,<2.0.0)
Requires-Dist: opencv-python (==4.5.5.64)
Requires-Dist: paddleocr (>=2.6.1.3,<3.0.0.0)
Requires-Dist: paddlepaddle (>=2.4.2,<3.0.0)
Requires-Dist: pillow (>=9.4.0,<10.0.0)
Requires-Dist: pyautogui (>=0.9.53,<0.10.0)
Requires-Dist: pynput (>=1.7.6,<2.0.0)
Requires-Dist: pyyaml (>=6.0,<7.0)
